README
pavement.py
setup.py
rusty/__init__.py
rusty/exceltable.py
rusty/includesh.py
rusty/regxlist.py
rusty/rolelist.py
rusty/util.py
rusty/xmltable.py
rusty.egg-info/PKG-INFO
rusty.egg-info/SOURCES.txt
rusty.egg-info/dependency_links.txt
rusty.egg-info/not-zip-safe
rusty.egg-info/requires.txt
rusty.egg-info/top_level.txt
test/test_all.py