Metadata-Version: 1.0
Name: rusty
Version: 0.3.1
Summary: A collection of Sphinx extensions
Home-page: http://jmu.koodiorja.com/projects/rusty/
Author: Juha Mustonen
Author-email: juha,p,mustonen(a)gmail.com
License: MIT
Download-URL: http://pypi.python.org/pypi/rusty/
Platform: any
Classifier: Development Status :: 3 - Alpha
Classifier: Environment :: Console
Classifier: Environment :: Web Environment
Classifier: Intended Audience :: Developers
Classifier: License :: OSI Approved :: MIT License
Classifier: Operating System :: OS Independent
Classifier: Programming Language :: Python
Classifier: Topic :: Documentation
Classifier: Topic :: Utilities
